{
  "docs": [
    {
      "type": "html",
      "value": "<strong>FluxNinja</strong>",
      "defaultStyle": "true"
    },
    { "type": "doc", "id": "fluxninja/introduction" },
    {
      "type": "autogenerated",
      "dirName": ".:Get Started"
    },
    { "type": "doc", "id": "fluxninja/extension" },
    {
      "type": "html",
      "value": "<strong>Aperture</strong>",
      "defaultStyle": "true"
    },
    {
      "type": "autogenerated",
      "dirName": ".:Introduction,Use Cases,Integrations,Architecture,Concepts,Self-Hosting,Reference,FAQ"
    },
    {
      "type": "link",
      "label": "Aperture @ GitHub",
      "href": "https://github.com/fluxninja/aperture"
    },
    {
      "type": "html",
      "value": "<hr/>",
      "defaultStyle": "true"
    },
    {
      "type": "link",
      "label": "FluxNinja Blog",
      "href": "https://blog.fluxninja.com/"
    },
    {
      "type": "link",
      "label": "Join Slack Community",
      "href": "https://join.slack.com/t/fluxninja-aperture/shared_invite/zt-1ewkfjfy9-~wF4EryoDyJ6kaPRTNZPyA"
    }
  ]
}
